duplo_resource/__init__.py
duplo_resource/ai.py
duplo_resource/asg.py
duplo_resource/aws_secret.py
duplo_resource/batch_compute.py
duplo_resource/batch_definition.py
duplo_resource/batch_job.py
duplo_resource/batch_queue.py
duplo_resource/batch_scheduling_policy.py
duplo_resource/cloudfront.py
duplo_resource/configmap.py
duplo_resource/cronjob.py
duplo_resource/ecs_service.py
duplo_resource/hosts.py
duplo_resource/infrastructure.py
duplo_resource/ingress.py
duplo_resource/jit.py
duplo_resource/job.py
duplo_resource/lambda.py
duplo_resource/plan.py
duplo_resource/pod.py
duplo_resource/pvc.py
duplo_resource/rds.py
duplo_resource/s3.py
duplo_resource/secret.py
duplo_resource/service.py
duplo_resource/ssm_param.py
duplo_resource/storageclass.py
duplo_resource/system.py
duplo_resource/tenant.py
duplo_resource/user.py
duplo_resource/version.py
duplocloud/__init__.py
duplocloud/args.py
duplocloud/argtype.py
duplocloud/cli.py
duplocloud/client.py
duplocloud/commander.py
duplocloud/errors.py
duplocloud/formats.py
duplocloud/resource.py
duplocloud/server.py
duplocloud_client-0.3.8.dist-info/licenses/LICENSE
duplocloud_client-0.3.8.dist-info/METADATA
duplocloud_client-0.3.8.dist-info/WHEEL
duplocloud_client-0.3.8.dist-info/entry_points.txt
duplocloud_client-0.3.8.dist-info/top_level.txt
duplocloud_client-0.3.8.dist-info/RECORD
