Metadata-Version: 2.4
Name: duplocloud-client
Version: 0.3.8
Summary: Command line Client for interacting with Duplocloud portals.
Author-email: Kelly <kelly@duplocloud.net>
Maintainer-email: Kelly <kelly@duplocloud.net>
Project-URL: Homepage, https://duplocloud.com/
Project-URL: Documentation, https://cli.duplocloud.com/
Project-URL: Repository, https://github.com/duplocloud/duploctl
Project-URL: Issues, https://github.com/duplocloud/duploctl/issues
Project-URL: Changelog, https://cli.duplocloud.com/Changelog
Project-URL: LatestRelease, https://github.com/duplocloud/duploctl/releases
Keywords: duplocloud,duplo,duploctl,duplo-client
Classifier: Programming Language :: Python :: 3
Classifier: License :: OSI Approved :: MIT License
Classifier: Operating System :: OS Independent
Requires-Python: >=3.10.0
License-File: LICENSE
Requires-Dist: requests>=2.22.0
Requires-Dist: cachetools>=5.2.0
Requires-Dist: jmespath>=1.0.1
Requires-Dist: pyyaml>=6.0.1
Requires-Dist: jsonpatch>=1.33
Requires-Dist: pyjwt>=2.8.0
Requires-Dist: jsonpointer>=2.4
Provides-Extra: build
Requires-Dist: invoke; extra == "build"
Requires-Dist: setuptools_scm; extra == "build"
Requires-Dist: build; extra == "build"
Requires-Dist: wheel; extra == "build"
Requires-Dist: twine; extra == "build"
Requires-Dist: pyinstaller; extra == "build"
Requires-Dist: toml; extra == "build"
Requires-Dist: semver; extra == "build"
Requires-Dist: GitPython; extra == "build"
Requires-Dist: Jinja2; extra == "build"
Provides-Extra: test
Requires-Dist: pytest; extra == "test"
Requires-Dist: ruff; extra == "test"
Requires-Dist: pip-audit; extra == "test"
Requires-Dist: pytest-black; extra == "test"
Requires-Dist: pytest-isort; extra == "test"
Requires-Dist: pytest-cov; extra == "test"
Requires-Dist: pytest-dependency; extra == "test"
Requires-Dist: pytest-order; extra == "test"
Requires-Dist: pytest-mock; extra == "test"
Provides-Extra: aws
Requires-Dist: boto3>=1.34.83; extra == "aws"
Provides-Extra: docs
Requires-Dist: mkdocs; extra == "docs"
Requires-Dist: mkdocs-material; extra == "docs"
Requires-Dist: mkdocstrings[python]; extra == "docs"
Dynamic: license-file
